{"title":{"rendered":"Daniel Glick-Unterman"},"meta":{"degree":"M.Arch I","graduation_year":"2017","folds_edited":[{"slug":"second-year-fold","meta":{"fold_front":{"media_details":{"sizes":{"full":{"source_url":"https://d2rpbtor0vesnk.cloudfront.net/wp-content/uploads/2018/08/22005113/Vol-01-Issue-05_The_Second_Year_Fold_Acheatel-Berkowitz-Carney-GU-Hardee-Hon-Muydinov_09-03-15_front.jpg"}}}}}},{"slug":"metrics","meta":{"fold_front":{"media_details":{"sizes":{"full":{"source_url":"https://d2rpbtor0vesnk.cloudfront.net/wp-content/uploads/2018/08/22005905/Vol-01-Issue-20_Metrics_Thissen-GU-Fisher_02-25-16_front.jpg"}}}}}}],"folds_designed":[],"posts_contributed":[{"title":{"rendered":"3 TABLES &#8211; 9 SITES"},"slug":"3-tables-9-sites","meta":{"contributors":[{"title":{"rendered":"Daniel Glick-Unterman"}}]}},{"title":{"rendered":"3 Days, 3 Publics: The State of the Art of Architecture at the Chicago Biennial."},"slug":"3-days-3-publics-the-state-of-the-art-of-architecture-at-the-chicago-biennial","meta":{"contributors":[{"title":{"rendered":"Misha Semenov"}},{"title":{"rendered":"Daniel Glick-Unterman"}}]}},{"title":{"rendered":"A Flexible Kink Fringe through Mercurial Windows"},"slug":"a-flexible-kink-fringe-through-mercurial-windows","meta":{"contributors":[{"title":{"rendered":"Daniel Glick-Unterman"}}]}},{"title":{"rendered":"Wear the Wig—Amnesty for the Fault of Icarus"},"slug":"wear-the-wig-amnesty-for-the-fault-of-icarus","meta":{"contributors":[{"title":{"rendered":"Daniel Glick-Unterman"}}]}},{"title":{"rendered":"about diagram 3: landscape with wing"},"slug":"about-diagram-3-landscape-with-wing","meta":{"contributors":[{"title":{"rendered":"Daniel Glick-Unterman"}}]}}]}}