{"title":{"rendered":"Priyanka Sheth"},"meta":{"degree":"M.Arch II","graduation_year":"2019","dual_degree":"","organization":false,"folds_edited":[{"slug":"canon","meta":{"fold_front":{"media_details":{"sizes":{"full":{"source_url":"https://d2rpbtor0vesnk.cloudfront.net/wp-content/uploads/2019/04/03115044/Canon-finalbw.jpg"}}}}}}],"folds_designed":[],"posts_contributed":[{"title":{"rendered":"(An)Architecture of Stepwells"},"slug":"anarchitecture-of-stepwells","meta":{"contributors":[{"title":{"rendered":"Priyanka Sheth"}}]}},{"title":{"rendered":"(Dis)Illusion"},"slug":"disillusion","meta":{"contributors":[{"title":{"rendered":"Priyanka Sheth"}}]}},{"title":{"rendered":"On Pedagogy and the “Canon”:  Interview with Esther da Costa Meyer"},"slug":"on-pedagogy-and-the-canon-interview-with-esther-da-costa-meyer","meta":{"contributors":[{"title":{"rendered":"Esther da Costa Meyer"}},{"title":{"rendered":"Dina Taha"}},{"title":{"rendered":"Priyanka Sheth"}}]}},{"title":{"rendered":"Blurred Boundaries"},"slug":"blurred-boundaries","meta":{"contributors":[{"title":{"rendered":"Priyanka Sheth"}}]}}]}}